pychemin/being.py
pychemin/characters.py
pychemin/cli.py
pychemin/constants.py
pychemin/debug.py
pychemin/exceptions.py
pychemin/grammar.lark
pychemin/main.py
pychemin/parser.py
pychemin/paths.py
pychemin/player.py
pychemin/stats.py
pychemin/ui.py
pychemin/walker.py
pychemin-0.0.1.dev2.dist-info/entry_points.txt
pychemin-0.0.1.dev2.dist-info/LICENSE
pychemin-0.0.1.dev2.dist-info/WHEEL
pychemin-0.0.1.dev2.dist-info/METADATA
pychemin-0.0.1.dev2.dist-info/RECORD
